{
    "version": "2.2.1",
    "description": "High-performance SOCKS5 proxifier for Windows built on NDISAPI.",
    "homepage": "https://github.com/wiresock/proxifyre",
    "license": "MIT",
    "depends": "ndisapi-np",
    "architecture": {
        "64bit": {
            "url": "https://github.com/wiresock/proxifyre/releases/download/v2.2.1/ProxiFyre-v2.2.1-x64-signed.zip",
            "hash": "c38ca1caa68cd730712f5c0911e4240711bf9e7684988ae64ed04ec693cce899"
        },
        "32bit": {
            "url": "https://github.com/wiresock/proxifyre/releases/download/v2.2.1/ProxiFyre-v2.2.1-x86-signed.zip",
            "hash": "4ae6614a776963191e7878432fb933282df9f5ab417e3a50fca8b7a876293030"
        },
        "arm64": {
            "url": "https://github.com/wiresock/proxifyre/releases/download/v2.2.1/ProxiFyre-v2.2.1-ARM64-signed.zip",
            "hash": "c68f2134879d426d6cc783a517dd5f37dbdd1860e33414e26aed587724882471"
        }
    },
    "pre_install": [
        "if (!(Test-Path \"$persist_dir\")) { New-Item \"$persist_dir\" -ItemType Directory -Force | Out-Null }",
        "if (!(Test-Path \"$persist_dir\\app-config.json\")) {",
        "    $config = @(",
        "        '{',",
        "        '  \"logLevel\": \"Info\",',",
        "        '  \"bypassLan\": true,',",
        "        '  \"proxies\": [',",
        "        '    {',",
        "        '      \"appNames\": [],',",
        "        '      \"socks5ProxyEndpoint\": \"127.0.0.1:1080\",',",
        "        '      \"supportedProtocols\": [\"TCP\", \"UDP\"]',",
        "        '    }',",
        "        '  ]',",
        "        '}'",
        "    )",
        "    $config | Set-Content \"$persist_dir\\app-config.json\" -Encoding Ascii",
        "}"
    ],
    "bin": "ProxiFyre.exe",
    "shortcuts": [
        [
            "ProxiFyre.exe",
            "ProxiFyre"
        ]
    ],
    "persist": "app-config.json",
    "checkver": "github",
    "autoupdate": {
        "architecture": {
            "64bit": {
                "url": "https://github.com/wiresock/proxifyre/releases/download/v$version/ProxiFyre-v$version-x64-signed.zip"
            },
            "32bit": {
                "url": "https://github.com/wiresock/proxifyre/releases/download/v$version/ProxiFyre-v$version-x86-signed.zip"
            },
            "arm64": {
                "url": "https://github.com/wiresock/proxifyre/releases/download/v$version/ProxiFyre-v$version-ARM64-signed.zip"
            }
        }
    }
}
